{"id": 249537, "title": "Брехт, Бертольт", "text": "Бертольт Брехт (нем. Bertolt Brecht; полное имя — Ойген Бертхольд Фридрих Брехт, Eugen Berthold Friedrich Brecht (); 10 февраля 1898, Аугсбург — 14 августа 1956, Берлин) — немецкий драматург, поэт, прозаик, театральный деятель, теоретик искусства, основатель театра «Берлинер ансамбль».\nТворчество Брехта — поэта и драматурга — всегда вызывало споры, как и его теория «эпического театра», и его политические взгляды. Тем не менее, уже в 50-х годах пьесы Брехта прочно вошли в европейский театральный репертуар; его идеи в той или иной форме были восприняты многими драматургами-современниками, в том числе Фридрихом Дюрренматтом, Артюром Адамовым, Максом Фришем, Хайнером Мюллером.\nТеория «эпического театра», в послевоенные годы претворённая в практику Брехтом-режиссёром, открыла принципиально новые возможности сценического искусства и оказала значительное влияние на развитие театра XX века.\n", "listWikiEntity": [{"currentText": "Бертольт Брехт", "startPosition": 0, "endPosition": 14, "id": ["Q38757", "Q13048269"]}, {"currentText": "Bertolt Brecht", "startPosition": 21, "endPosition": 35, "id": ["Q38757", "Q828370"]}, {"currentText": "Ойген Бертхольд Фридрих Брехт", "startPosition": 50, "endPosition": 79, "id": -1}, {"currentText": "Аугсбург", "startPosition": 134, "endPosition": 142, "id": ["Q15755", "Q2749", "Q10414"]}, {"currentText": "Берлин", "startPosition": 162, "endPosition": 168, "id": ["Q64", "Q102720", "Q56037"]}, {"currentText": "Берлинер ансамбль", "startPosition": 267, "endPosition": 284, "id": ["Q534914", "Q9453474"]}, {"currentText": "Брехта", "startPosition": 298, "endPosition": 304, "id": ["Q6328136", "Q38757", "Q7041721"]}, {"currentText": "Брехта", "startPosition": 454, "endPosition": 460, "id": ["Q38757", "Q6328136", "Q7041721"]}, {"currentText": "Фридрихом Дюрренматтом", "startPosition": 606, "endPosition": 628, "id": -1}, {"currentText": "Артюром Адамовым", "startPosition": 630, "endPosition": 646, "id": -1}, {"currentText": "Максом Фришем", "startPosition": 648, "endPosition": 661, "id": -1}, {"currentText": "Хайнером Мюллером", "startPosition": 663, "endPosition": 680, "id": -1}]}