{"id": 196460, "title": "Исидор Севильский", "text": "Святой Исидор Севильский (исп. San Isidoro de Sevilla), иначе Исидор Гиспальский (лат. Isidorus Hispalensis), или Исидор Младший (лат. Isidorus Iunior) (между 560—570, Гиспала, Вестготское королевство — 4 апреля 636, там же) — архиепископ Гиспалы (Севильи) в вестготской Испании (600/601—636), последний латинский отец Церкви, компилятор мосарабского богослужебного обряда. Наиболее известен как основатель средневекового энциклопедизма и плодовитый церковный писатель. Magnum opus — «Этимологии» в 20 книгах, универсальная энциклопедия, систематизирующая сумму позднеантичного знания в соответствии с христианскими представлениями.\nПо отцу происходил из знатного испано-римского рода, по матери, предположительно, — от вестготских королей. Наследовав около 600 или 601 года гиспальскую архиепископскую кафедру у старшего брата Леандра, активно участвовал в политической жизни Толедского королевства. На посту епископа стремился проводить политику этнической и политической консолидации государства на основе кафолического исповедания. В русле этой политики принимались решения созванных при его участии Второго Севильского (619) и Четвёртого Толедского соборов (633). До самой кончины Исидор Севильский имел значительное влияние на политику королей Лиувы II, Виттериха, Гундемара, Сисебута (ученик архиепископа), Реккареда II, Свинтилы и Сисенанда (узурпатор, чьи действия были санкционированы архиепископом Гиспалы).\nПочитался как святой и чудотворец ещё с IX века, в 1598 году был канонизирован Римской католической церковью, в 1722 году провозглашён Учителем Церкви. Его старшие братья Леандр и Фульгенций, а также сестра Флорентина, были причислены к лику святых. С конца 1990-х годов стал широко известен как святой покровитель Интернета, существует виртуальный Орден св. Исидора Севильского.\n", "listWikiEntity": [{"currentText": "Исидор Севильский", "startPosition": 7, "endPosition": 24, "id": ["Q166876"]}, {"currentText": "San Isidoro de Sevilla", "startPosition": 31, "endPosition": 53, "id": ["Q166876"]}, {"currentText": "Исидор Гиспальский", "startPosition": 62, "endPosition": 80, "id": ["Q166876"]}, {"currentText": "Isidorus Hispalensis", "startPosition": 87, "endPosition": 107, "id": ["Q166876"]}, {"currentText": "Исидор Младший", "startPosition": 114, "endPosition": 128, "id": ["Q166876"]}, {"currentText": "Isidorus", "startPosition": 135, "endPosition": 143, "id": ["Q166876"]}, {"currentText": "Вестготское королевство", "startPosition": 177, "endPosition": 200, "id": ["Q126936"]}, {"currentText": "Magnum", "startPosition": 470, "endPosition": 476, "id": ["Q1962746", "Q372899", "Q1754885"]}, {"currentText": "По", "startPosition": 633, "endPosition": 635, "id": ["Q643", "Q132671", "Q681862"]}, {"currentText": "Леандра", "startPosition": 828, "endPosition": 835, "id": ["Q20942976"]}, {"currentText": "На посту", "startPosition": 901, "endPosition": 909, "id": ["Q4311001"]}, {"currentText": "До", "startPosition": 1169, "endPosition": 1171, "id": ["Q1432210", "Q475885", "Q1263489"]}, {"currentText": "Исидор Севильский", "startPosition": 1186, "endPosition": 1203, "id": ["Q166876"]}, {"currentText": "II", "startPosition": 1256, "endPosition": 1258, "id": ["Q314791", "Q209118", "Q312605"]}, {"currentText": "II", "startPosition": 1324, "endPosition": 1326, "id": ["Q314791", "Q209118", "Q312605"]}, {"currentText": "святой", "startPosition": 1433, "endPosition": 1439, "id": ["Q48068543"]}, {"currentText": "IX", "startPosition": 1459, "endPosition": 1461, "id": ["Q623740", "Q20862968", "Q264947"]}, {"currentText": "Фульгенций", "startPosition": 1599, "endPosition": 1609, "id": ["Q2616176"]}, {"currentText": "святой", "startPosition": 1715, "endPosition": 1721, "id": ["Q48068543"]}, {"currentText": "Орден", "startPosition": 1768, "endPosition": 1773, "id": ["Q1164783", "Q1116670"]}, {"currentText": "Исидора", "startPosition": 1778, "endPosition": 1785, "id": ["Q1093812"]}]}