{"id": 3162337, "title": "Убийство Георгия Гапона", "text": "Убийство Георгия Гапона — одно из нераскрытых политических убийств в России. Жертвой убийства стал 36-летний политик и общественный деятель, руководитель Собрания русских фабрично-заводских рабочих Санкт-Петербурга, бывший священник Георгий Аполлонович Гапон. Убийство произошло 28 марта (10 апреля) 1906 года в пригороде Санкт-Петербурга, дачном посёлке Озерки. Никто из убийц не был арестован и не предстал перед судом. Возбуждённое следствие не привело ни к каким результатам и через несколько лет было закрыто. Материалы следственного дела остались необнародованными. Известно, что в качестве главного подозреваемого в следственном деле фигурировал член партии эсеров, инженер Пётр Моисеевич Рутенберг. Через несколько лет после убийства, в 1909 году, Рутенберг обнародовал заявление, в котором признавал, что совершил убийство Гапона по поручению центрального комитета (ЦК) партии эсеров. По утверждению Рутенберга, инициатором и главным организатором убийства был глава Боевой организации эсеров, секретный сотрудник Департамента полиции, инженер Евгений Филиппович Азеф. Заявление Рутенберга было официально подтверждено ЦК партии эсеров и Судебно-следственной комиссией партии эсеров по делу Азефа. Впоследствии в советской историографии получил хождение миф, согласно которому Гапон был «судим группой рабочих». Этот миф противоречит как заявлениям Рутенберга и ЦК партии эсеров, так и воспоминаниям самих исполнителей убийства, утверждавших, что, убивая Гапона, они исполняли решение ЦК.\n", "listWikiEntity": [{"currentText": "Георгия Гапона", "startPosition": 9, "endPosition": 23, "id": ["Q19153035", "Q299681", "Q299681"]}, {"currentText": "России", "startPosition": 69, "endPosition": 75, "id": ["Q151469", "Q151469", "Q151469"]}, {"currentText": "Собрания русских фабрично-заводских рабочих", "startPosition": 154, "endPosition": 197, "id": -1}, {"currentText": "Санкт-Петербурга", "startPosition": 198, "endPosition": 214, "id": ["Q656", "Q656", "Q656"]}, {"currentText": "Георгий Аполлонович Гапон", "startPosition": 233, "endPosition": 258, "id": ["Q299681", "Q299681", "Q299681"]}, {"currentText": "Санкт-Петербурга", "startPosition": 322, "endPosition": 338, "id": ["Q656", "Q656", "Q656"]}, {"currentText": "Озерки", "startPosition": 355, "endPosition": 361, "id": ["Q4332023", "Q4332023", "Q4332020"]}, {"currentText": "Пётр Моисеевич Рутенберг", "startPosition": 681, "endPosition": 705, "id": ["Q475380", "Q475380"]}, {"currentText": "Рутенберг", "startPosition": 756, "endPosition": 765, "id": ["Q475380", "Q475380", "Q1065967"]}, {"currentText": "Гапона", "startPosition": 832, "endPosition": 838, "id": ["Q299681", "Q299681", "Q299681"]}, {"currentText": "Рутенберга", "startPosition": 909, "endPosition": 919, "id": -1}, {"currentText": "Боевой организации эсеров", "startPosition": 976, "endPosition": 1001, "id": -1}, {"currentText": "Департамента полиции", "startPosition": 1023, "endPosition": 1043, "id": ["Q328473", "Q328473", "Q328473"]}, {"currentText": "Евгений Филиппович Азеф", "startPosition": 1053, "endPosition": 1076, "id": ["Q171930", "Q171930", "Q171930"]}, {"currentText": "Рутенберга", "startPosition": 1088, "endPosition": 1098, "id": -1}, {"currentText": "ЦК", "startPosition": 1128, "endPosition": 1130, "id": ["Q1971373", "Q1971373", "Q1971373"]}, {"currentText": "Судебно-следственной комиссией", "startPosition": 1147, "endPosition": 1177, "id": -1}, {"currentText": "Азефа", "startPosition": 1200, "endPosition": 1205, "id": ["Q19216154"]}, {"currentText": "Гапон", "startPosition": 1286, "endPosition": 1291, "id": ["Q299681", "Q299681", "Q299681"]}, {"currentText": "Рутенберга", "startPosition": 1358, "endPosition": 1368, "id": -1}, {"currentText": "ЦК", "startPosition": 1371, "endPosition": 1373, "id": ["Q1971373", "Q1971373", "Q1971373"]}, {"currentText": "Гапона", "startPosition": 1464, "endPosition": 1470, "id": ["Q299681", "Q299681", "Q299681"]}, {"currentText": "ЦК", "startPosition": 1494, "endPosition": 1496, "id": ["Q1971373", "Q1971373", "Q1971373"]}]}